tgconvert/__init__.py
tgconvert/base.py
tgconvert/cli.py
tgconvert/converter.py
tgconvert/accs/tdata/D877F783D5D3EF8Cs
tgconvert/accs/tdata/key_datas
tgconvert/accs/tdata/D877F783D5D3EF8C/maps
tgconvert/formats/__init__.py
tgconvert/formats/authkey.py
tgconvert/formats/pyrogram.py
tgconvert/formats/tdata.py
tgconvert/formats/telethon.py
tgconvert-0.1.0.dist-info/licenses/LICENSE
tgconvert-0.1.0.dist-info/METADATA
tgconvert-0.1.0.dist-info/WHEEL
tgconvert-0.1.0.dist-info/entry_points.txt
tgconvert-0.1.0.dist-info/top_level.txt
tgconvert-0.1.0.dist-info/RECORD
